README.md
setup.cfg
setup.py
pynion/__init__.py
pynion/__main__.py
pynion.egg-info/PKG-INFO
pynion.egg-info/SOURCES.txt
pynion.egg-info/dependency_links.txt
pynion.egg-info/entry_points.txt
pynion.egg-info/not-zip-safe
pynion.egg-info/requires.txt
pynion.egg-info/top_level.txt
pynion/abstractclass/__init__.py
pynion/abstractclass/jsoner.py
pynion/abstractclass/numpy_handlers.py
pynion/config/default.settings
pynion/config/user.settings
pynion/decorators/__init__.py
pynion/decorators/accepts.py
pynion/decorators/extendable.py
pynion/errors/__init__.py
pynion/errors/fe.py
pynion/errors/ffe.py
pynion/errors/mtce.py
pynion/errors/pe.py
pynion/errors/xe.py
pynion/filesystem/__init__.py
pynion/filesystem/filefactory.py
pynion/filesystem/path.py
pynion/filesystem/_filetypes/__init__.py
pynion/filesystem/_filetypes/basefile.py
pynion/filesystem/_filetypes/compressedfile.py
pynion/filesystem/_filetypes/containerfile.py
pynion/main/__init__.py
pynion/main/executable.py
pynion/main/manager.py
pynion/main/_inner/__init__.py
pynion/main/_inner/experiment.py
pynion/main/_inner/process.py
pynion/main/_inner/project.py
pynion/metaclass/__init__.py
pynion/metaclass/tones.py