Metadata-Version: 1.1
Name: pynion
Version: 0.0.4
Summary: Python Minion Library
Home-page: https://github.com/jaumebonet/pynion
Author: Jaume Bonet
Author-email: jaume.bonet@gmail.com
License: MIT
Download-URL: https://github.com/jaumebonet/pynion/archive/0.0.4.tar.gz
Keywords: development
Platform: UNIX
Classifier: Development Status :: 3 - Alpha
Classifier: Intended Audience :: Developers
Classifier: Topic :: Software Development :: Build Tools
Classifier: License :: OSI Approved :: MIT License
Classifier: Programming Language :: Python :: 2
Classifier: Programming Language :: Python :: 2.6
Classifier: Programming Language :: Python :: 2.7
Classifier: Programming Language :: Python :: 3
Classifier: Programming Language :: Python :: 3.2
Classifier: Programming Language :: Python :: 3.3
Classifier: Programming Language :: Python :: 3.4
